README.md
setup.py
ket/__init__.py
ket/bitbucket.py
ket/cli.py
ket/repo.py
ket/utils.py
ket.egg-info/PKG-INFO
ket.egg-info/SOURCES.txt
ket.egg-info/dependency_links.txt
ket.egg-info/entry_points.txt
ket.egg-info/requires.txt
ket.egg-info/top_level.txt