Metadata-Version: 2.1
Name: ket
Version: 0.0.4
Summary: Bitbucket workflows in your terminal
Home-page: https://github.com/Ch00k/ket
Author: Andrii Yurchuk
Author-email: ay@mntw.re
License: MIT
Platform: UNKNOWN
Classifier: Environment :: Console
Classifier: Intended Audience :: Developers
Classifier: Intended Audience :: Information Technology
Classifier: License :: OSI Approved :: MIT License
Classifier: Operating System :: Unix
Classifier: Programming Language :: Python
Classifier: Programming Language :: Python :: 3.6
Classifier: Programming Language :: Python :: 3.7
Classifier: Topic :: Software Development
Classifier: Topic :: Software Development :: Version Control
Classifier: Topic :: Software Development :: Version Control :: Git
